ccjtools/__init__.py
ccjtools/ccj_make.py
ccjtools/ccj_xform_ap.py
ccjtools/ccj_xform_px4.py
ccjtools-0.1.0.data/scripts/ccj-make
ccjtools-0.1.0.data/scripts/ccj-xform-ap
ccjtools-0.1.0.data/scripts/ccj-xform-px4
tests/__init__.py
tests/test_argParse.py
tests/test_detectCompileCommand.py
tests/test_inputFile.py
tests/test_mcux.py
tests/test_singleLines.py
ccjtools-0.1.0.dist-info/LICENSE
ccjtools-0.1.0.dist-info/METADATA
ccjtools-0.1.0.dist-info/WHEEL
ccjtools-0.1.0.dist-info/top_level.txt
ccjtools-0.1.0.dist-info/RECORD
