Metadata-Version: 2.1
Name: ccjtools
Version: 0.1.0
Summary: Scripts for working with JSON compilation databases for clang etc.
Home-page: https://github.com/langrind/ccjtools
Author: Nik Langrind
Author-email: langrind@gmail.com
License: MIT
Platform: UNKNOWN
Classifier: Programming Language :: Python :: 3
Classifier: License :: OSI Approved :: MIT License
Classifier: Operating System :: OS Independent
Requires-Python: >=3.6
